vast_ai_api/__init__.py
vast_ai_api/util.py
vast_ai_api/vast_ai.py
vast_ai_api-1.0.0.dist-info/LICENSE
vast_ai_api-1.0.0.dist-info/METADATA
vast_ai_api-1.0.0.dist-info/WHEEL
vast_ai_api-1.0.0.dist-info/RECORD
