Metadata-Version: 2.1
Name: vast-ai-api
Version: 1.0.0
Summary: A Vast.ai API helper
Home-page: https://github.com/KianShah/vast-ai-api
License: MIT
Author: Kian
Author-email: kianshah376@gmail.com
Requires-Python: >=3.10,<3.11
Classifier: License :: OSI Approved :: MIT License
Classifier: Programming Language :: Python :: 3
Classifier: Programming Language :: Python :: 3.10
Requires-Dist: pandas (>=2.1.4,<3.0.0)
Requires-Dist: paramiko (>=3.4.0,<4.0.0)
Requires-Dist: requests (>=2.31.0,<3.0.0)
Project-URL: Repository, https://github.com/KianShah/vast-ai-api
